{
	"@type":"Process",
	"Name":"}pa_camidtogroup",
	"HasSecurityAccess":false,
	"Code@Code.link":"}pa_camidtogroup.ti",
	"UIData":"CubeAction=1511\fDataAction=1503\fCubeLogChanges=0\f",
	"VariablesUIData":
	[
		"VarType=32\fColType=827\f",
		"VarType=32\fColType=827\f",
		"VarType=32\fColType=827\f"
	],
	"DataSource":
	{
		"Type":"ASCII",
		"asciiDecimalSeparator":".",
		"asciiDelimiterChar":",",
		"asciiDelimiterType":"Character",
		"asciiHeaderRecords":0,
		"asciiQuoteCharacter":"",
		"asciiThousandSeparator":",",
		"dataSourceNameForClient":"CAMIDToGroup.txt",
		"dataSourceNameForServer":"CAMIDToGroup.txt"
	},
	"Parameters":[],
	"Variables":
	[
		{
			"Name":"vGroupName",
			"Type":"String",
			"Position":1,
			"StartByte":0,
			"EndByte":0
		},
		{
			"Name":"vCAMID",
			"Type":"String",
			"Position":2,
			"StartByte":0,
			"EndByte":0
		},
		{
			"Name":"vCAMIDDisplayValue",
			"Type":"String",
			"Position":3,
			"StartByte":0,
			"EndByte":0
		}
	]
}