{
	"@type":"NativeView",
	"Name":"Units by Model Variances",
	"Columns":
	[
		{
			"Subset":
			{
				"Hierarchy":
				{
					"@id":"Dimensions('actvsbud')/Hierarchies('actvsbud')"
				},
				"Expression":"TM1SubsetAll([actvsbud])"
			}
		},
		{
			"Subset":
			{
				"Hierarchy":
				{
					"@id":"Dimensions('month')/Hierarchies('month')"
				},
				"Expression":"TM1SubsetAll([month])"
			}
		}
	],
	"Rows":
	[
		{
			"Subset":
			{
				"Hierarchy":
				{
					"@id":"Dimensions('model')/Hierarchies('model')"
				},
				"Elements":
				[
					{
						"@id":"Dimensions('model')/Hierarchies('model')/Elements('Total')"
					},
					{
						"@id":"Dimensions('model')/Hierarchies('model')/Elements('S Series')"
					},
					{
						"@id":"Dimensions('model')/Hierarchies('model')/Elements('S Series Sedan')"
					},
					{
						"@id":"Dimensions('model')/Hierarchies('model')/Elements('S Series Wagon')"
					},
					{
						"@id":"Dimensions('model')/Hierarchies('model')/Elements('L Series')"
					},
					{
						"@id":"Dimensions('model')/Hierarchies('model')/Elements('L Series Sedan')"
					},
					{
						"@id":"Dimensions('model')/Hierarchies('model')/Elements('L Series Wagon')"
					},
					{
						"@id":"Dimensions('model')/Hierarchies('model')/Elements('L Series Convertible')"
					},
					{
						"@id":"Dimensions('model')/Hierarchies('model')/Elements('T Series')"
					},
					{
						"@id":"Dimensions('model')/Hierarchies('model')/Elements('T Series Sedan')"
					},
					{
						"@id":"Dimensions('model')/Hierarchies('model')/Elements('T Series Coupe')"
					}
				]
			}
		}
	],
	"Titles":
	[
		{
			"Subset":
			{
				"Hierarchy":
				{
					"@id":"Dimensions('region')/Hierarchies('region')"
				},
				"Elements":
				[
					{
						"@id":"Dimensions('region')/Hierarchies('region')/Elements('World')"
					},
					{
						"@id":"Dimensions('region')/Hierarchies('region')/Elements('Europe')"
					},
					{
						"@id":"Dimensions('region')/Hierarchies('region')/Elements('Scandinavia')"
					},
					{
						"@id":"Dimensions('region')/Hierarchies('region')/Elements('Denmark')"
					},
					{
						"@id":"Dimensions('region')/Hierarchies('region')/Elements('Norway')"
					},
					{
						"@id":"Dimensions('region')/Hierarchies('region')/Elements('Sweden')"
					},
					{
						"@id":"Dimensions('region')/Hierarchies('region')/Elements('Benelux')"
					},
					{
						"@id":"Dimensions('region')/Hierarchies('region')/Elements('Islands')"
					},
					{
						"@id":"Dimensions('region')/Hierarchies('region')/Elements('Central Europe')"
					},
					{
						"@id":"Dimensions('region')/Hierarchies('region')/Elements('Iberia')"
					},
					{
						"@id":"Dimensions('region')/Hierarchies('region')/Elements('Southern Europe')"
					},
					{
						"@id":"Dimensions('region')/Hierarchies('region')/Elements('Americas')"
					}
				]
			},
			"Selected":
			{
				"@id":"Dimensions('region')/Hierarchies('region')/Elements('Denmark')"
			}
		},
		{
			"Subset":
			{
				"Hierarchy":
				{
					"@id":"Dimensions('account1')/Hierarchies('account1')"
				},
				"Elements":
				[
					{
						"@id":"Dimensions('account1')/Hierarchies('account1')/Elements('Gross Margin')"
					},
					{
						"@id":"Dimensions('account1')/Hierarchies('account1')/Elements('Gross Margin%')"
					},
					{
						"@id":"Dimensions('account1')/Hierarchies('account1')/Elements('Price')"
					},
					{
						"@id":"Dimensions('account1')/Hierarchies('account1')/Elements('Units')"
					},
					{
						"@id":"Dimensions('account1')/Hierarchies('account1')/Elements('Sales')"
					},
					{
						"@id":"Dimensions('account1')/Hierarchies('account1')/Elements('Promotional Sales')"
					},
					{
						"@id":"Dimensions('account1')/Hierarchies('account1')/Elements('Variable Costs')"
					}
				]
			},
			"Selected":
			{
				"@id":"Dimensions('account1')/Hierarchies('account1')/Elements('Units')"
			}
		}
	],
	"SuppressEmptyColumns":false,
	"SuppressEmptyRows":false,
	"FormatString":"0.#########"
}